[
    {
        "id": 1,
        "imagen": "https://images.pexels.com/photos/1571450/pexels-photo-1571450.jpeg?cs=srgb&dl=pexels-vecislavas-popa-1571450.jpg&fm=jpg",
        "titulo": "Cuarto 1"
    },
    {
        "id": 2,
        "imagen": "https://images.pexels.com/photos/8082562/pexels-photo-8082562.jpeg?auto=compress&cs=tinysrgb&w=600&lazy=load",
        "titulo": "Cuarto 2"
    },
    {
        "id": 3,
        "imagen": "https://images.pexels.com/photos/9209422/pexels-photo-9209422.jpeg?auto=compress&cs=tinysrgb&w=600&lazy=load",
        "titulo": "Cuarto 3"
    },
    {
        "id": 4,
        "imagen": "https://images.pexels.com/photos/2029731/pexels-photo-2029731.jpeg?auto=compress&cs=tinysrgb&w=600&lazy=load",
        "titulo": "Cuarto 4"
    }
]